{
	"$schema": "http://schema.management.azure.com/schemas/2015-01-01/deploymentTemplate.json#",
	"contentVersion": "1.0.0.0",
	"parameters": {
		"factoryName": {
			"type": "string",
			"metadata": "Data Factory name",
			"defaultValue": "adfdemojitendra1"
		},
		"flowlet_dep_dataset_connectionString": {
			"type": "secureString",
			"metadata": "Secure string for 'connectionString' of 'flowlet_dep_dataset'"
		},
		"flowletemp_dataset_connectionString": {
			"type": "secureString",
			"metadata": "Secure string for 'connectionString' of 'flowletemp_dataset'"
		},
		"flowletotpt_dataset_connectionString": {
			"type": "secureString",
			"metadata": "Secure string for 'connectionString' of 'flowletotpt_dataset'"
		},
		"fuzzyemp2_linkedservice_connectionString": {
			"type": "secureString",
			"metadata": "Secure string for 'connectionString' of 'fuzzyemp2_linkedservice'"
		},
		"fuzzyjoin_linkedservice_connectionString": {
			"type": "secureString",
			"metadata": "Secure string for 'connectionString' of 'fuzzyjoin_linkedservice'"
		},
		"fuzzyotpt_linkedservice_connectionString": {
			"type": "secureString",
			"metadata": "Secure string for 'connectionString' of 'fuzzyotpt_linkedservice'"
		},
		"jsonotpt_linkedservice_connectionString": {
			"type": "secureString",
			"metadata": "Secure string for 'connectionString' of 'jsonotpt_linkedservice'"
		},
		"parametarizelks_advanced_connectionString": {
			"type": "secureString",
			"metadata": "Secure string for 'connectionString' of 'parametarizelks_advanced'",
			"defaultValue": "Integrated Security=False;Encrypt=True;Connection Timeout=30;Data Source=tcp:@{linkedService().Server},1433;Initial Catalog=@{linkedService().DBName};User ID=@{linkedService().user};Password=@{linkedService().password};Trusted_Connection=False"
		},
		"parsecoldata_linkedservice_password": {
			"type": "secureString",
			"metadata": "Secure string for 'password' of 'parsecoldata_linkedservice'"
		},
		"parseotpt1_linkedservice_connectionString": {
			"type": "secureString",
			"metadata": "Secure string for 'connectionString' of 'parseotpt1_linkedservice'"
		},
		"parseotpt_linkedservice_password": {
			"type": "secureString",
			"metadata": "Secure string for 'password' of 'parseotpt_linkedservice'"
		},
		"parsetrans_linkedservice_password": {
			"type": "secureString",
			"metadata": "Secure string for 'password' of 'parsetrans_linkedservice'"
		},
		"parsetransotpt_linkedservice_connectionString": {
			"type": "secureString",
			"metadata": "Secure string for 'connectionString' of 'parsetransotpt_linkedservice'"
		},
		"rtntopipe_dataset_password": {
			"type": "secureString",
			"metadata": "Secure string for 'password' of 'rtntopipe_dataset'"
		},
		"rtntopipe_linkedservice_connectionString": {
			"type": "secureString",
			"metadata": "Secure string for 'connectionString' of 'rtntopipe_linkedservice'"
		},
		"rtntopipeotpt_linkedservice_connectionString": {
			"type": "secureString",
			"metadata": "Secure string for 'connectionString' of 'rtntopipeotpt_linkedservice'"
		},
		"stringify_linkedservice_connectionString": {
			"type": "secureString",
			"metadata": "Secure string for 'connectionString' of 'stringify_linkedservice'"
		},
		"stringifyotpt_linkedservice_connectionString": {
			"type": "secureString",
			"metadata": "Secure string for 'connectionString' of 'stringifyotpt_linkedservice'"
		},
		"template1_linkedservice_connectionString": {
			"type": "secureString",
			"metadata": "Secure string for 'connectionString' of 'template1_linkedservice'"
		},
		"template_linkedservice_connectionString": {
			"type": "secureString",
			"metadata": "Secure string for 'connectionString' of 'template_linkedservice'"
		},
		"parsecoldata_linkedservice_properties_typeProperties_server": {
			"type": "string",
			"defaultValue": "prodstd.database.windows.net"
		},
		"parsecoldata_linkedservice_properties_typeProperties_database": {
			"type": "string",
			"defaultValue": "TESTDB"
		},
		"parsecoldata_linkedservice_properties_typeProperties_userName": {
			"type": "string",
			"defaultValue": "jitendra"
		},
		"parseotpt_linkedservice_properties_typeProperties_server": {
			"type": "string",
			"defaultValue": "prodstd.database.windows.net"
		},
		"parseotpt_linkedservice_properties_typeProperties_database": {
			"type": "string",
			"defaultValue": "TESTDB"
		},
		"parseotpt_linkedservice_properties_typeProperties_userName": {
			"type": "string",
			"defaultValue": "jitendra"
		},
		"parsetrans_linkedservice_properties_typeProperties_server": {
			"type": "string",
			"defaultValue": "prodstd.database.windows.net"
		},
		"parsetrans_linkedservice_properties_typeProperties_database": {
			"type": "string",
			"defaultValue": "TESTDB"
		},
		"parsetrans_linkedservice_properties_typeProperties_userName": {
			"type": "string",
			"defaultValue": "jitendra"
		},
		"rtntopipe_dataset_properties_typeProperties_server": {
			"type": "string",
			"defaultValue": "prodstd.database.windows.net"
		},
		"rtntopipe_dataset_properties_typeProperties_database": {
			"type": "string",
			"defaultValue": "TESTDB"
		},
		"rtntopipe_dataset_properties_typeProperties_userName": {
			"type": "string",
			"defaultValue": "jitendra"
		}
	},
	"variables": {
		"factoryId": "[concat('Microsoft.DataFactory/factories/', parameters('factoryName'))]"
	},
	"resources": [
		{
			"name": "[concat(parameters('factoryName'), '/flowlet_dep_dataset')]",
			"type": "Microsoft.DataFactory/factories/linkedServices",
			"apiVersion": "2018-06-01",
			"properties": {
				"annotations": [],
				"type": "AzureBlobStorage",
				"typeProperties": {
					"connectionString": "[parameters('flowlet_dep_dataset_connectionString')]"
				}
			},
			"dependsOn": []
		},
		{
			"name": "[concat(parameters('factoryName'), '/flowletemp_dataset')]",
			"type": "Microsoft.DataFactory/factories/linkedServices",
			"apiVersion": "2018-06-01",
			"properties": {
				"annotations": [],
				"type": "AzureBlobStorage",
				"typeProperties": {
					"connectionString": "[parameters('flowletemp_dataset_connectionString')]"
				}
			},
			"dependsOn": []
		},
		{
			"name": "[concat(parameters('factoryName'), '/flowletotpt_dataset')]",
			"type": "Microsoft.DataFactory/factories/linkedServices",
			"apiVersion": "2018-06-01",
			"properties": {
				"annotations": [],
				"type": "AzureBlobStorage",
				"typeProperties": {
					"connectionString": "[parameters('flowletotpt_dataset_connectionString')]"
				}
			},
			"dependsOn": []
		},
		{
			"name": "[concat(parameters('factoryName'), '/fuzzyemp2_linkedservice')]",
			"type": "Microsoft.DataFactory/factories/linkedServices",
			"apiVersion": "2018-06-01",
			"properties": {
				"annotations": [],
				"type": "AzureBlobStorage",
				"typeProperties": {
					"connectionString": "[parameters('fuzzyemp2_linkedservice_connectionString')]"
				}
			},
			"dependsOn": []
		},
		{
			"name": "[concat(parameters('factoryName'), '/fuzzyjoin_linkedservice')]",
			"type": "Microsoft.DataFactory/factories/linkedServices",
			"apiVersion": "2018-06-01",
			"properties": {
				"annotations": [],
				"type": "AzureBlobStorage",
				"typeProperties": {
					"connectionString": "[parameters('fuzzyjoin_linkedservice_connectionString')]"
				}
			},
			"dependsOn": []
		},
		{
			"name": "[concat(parameters('factoryName'), '/fuzzyotpt_linkedservice')]",
			"type": "Microsoft.DataFactory/factories/linkedServices",
			"apiVersion": "2018-06-01",
			"properties": {
				"annotations": [],
				"type": "AzureBlobStorage",
				"typeProperties": {
					"connectionString": "[parameters('fuzzyotpt_linkedservice_connectionString')]"
				}
			},
			"dependsOn": []
		},
		{
			"name": "[concat(parameters('factoryName'), '/jsonotpt_linkedservice')]",
			"type": "Microsoft.DataFactory/factories/linkedServices",
			"apiVersion": "2018-06-01",
			"properties": {
				"annotations": [],
				"type": "AzureBlobStorage",
				"typeProperties": {
					"connectionString": "[parameters('jsonotpt_linkedservice_connectionString')]"
				}
			},
			"dependsOn": []
		},
		{
			"name": "[concat(parameters('factoryName'), '/parametarizelks_advanced')]",
			"type": "Microsoft.DataFactory/factories/linkedServices",
			"apiVersion": "2018-06-01",
			"properties": {
				"parameters": {
					"Server": {
						"type": "String"
					},
					"DBName": {
						"type": "String"
					},
					"user": {
						"type": "String"
					},
					"password": {
						"type": "String"
					}
				},
				"annotations": [],
				"type": "AzureSqlDatabase",
				"typeProperties": {
					"connectionString": "[parameters('parametarizelks_advanced_connectionString')]"
				}
			},
			"dependsOn": []
		},
		{
			"name": "[concat(parameters('factoryName'), '/parsecoldata_linkedservice')]",
			"type": "Microsoft.DataFactory/factories/linkedServices",
			"apiVersion": "2018-06-01",
			"properties": {
				"annotations": [],
				"type": "AzureSqlDatabase",
				"typeProperties": {
					"server": "[parameters('parsecoldata_linkedservice_properties_typeProperties_server')]",
					"database": "[parameters('parsecoldata_linkedservice_properties_typeProperties_database')]",
					"encrypt": "mandatory",
					"trustServerCertificate": false,
					"authenticationType": "SQL",
					"userName": "[parameters('parsecoldata_linkedservice_properties_typeProperties_userName')]",
					"password": {
						"type": "SecureString",
						"value": "[parameters('parsecoldata_linkedservice_password')]"
					}
				}
			},
			"dependsOn": []
		},
		{
			"name": "[concat(parameters('factoryName'), '/parseotpt1_linkedservice')]",
			"type": "Microsoft.DataFactory/factories/linkedServices",
			"apiVersion": "2018-06-01",
			"properties": {
				"annotations": [],
				"type": "AzureBlobStorage",
				"typeProperties": {
					"connectionString": "[parameters('parseotpt1_linkedservice_connectionString')]"
				}
			},
			"dependsOn": []
		},
		{
			"name": "[concat(parameters('factoryName'), '/parseotpt_linkedservice')]",
			"type": "Microsoft.DataFactory/factories/linkedServices",
			"apiVersion": "2018-06-01",
			"properties": {
				"annotations": [],
				"type": "AzureSqlDatabase",
				"typeProperties": {
					"server": "[parameters('parseotpt_linkedservice_properties_typeProperties_server')]",
					"database": "[parameters('parseotpt_linkedservice_properties_typeProperties_database')]",
					"encrypt": "mandatory",
					"trustServerCertificate": false,
					"authenticationType": "SQL",
					"userName": "[parameters('parseotpt_linkedservice_properties_typeProperties_userName')]",
					"password": {
						"type": "SecureString",
						"value": "[parameters('parseotpt_linkedservice_password')]"
					}
				}
			},
			"dependsOn": []
		},
		{
			"name": "[concat(parameters('factoryName'), '/parsetrans_linkedservice')]",
			"type": "Microsoft.DataFactory/factories/linkedServices",
			"apiVersion": "2018-06-01",
			"properties": {
				"annotations": [],
				"type": "AzureSqlDatabase",
				"typeProperties": {
					"server": "[parameters('parsetrans_linkedservice_properties_typeProperties_server')]",
					"database": "[parameters('parsetrans_linkedservice_properties_typeProperties_database')]",
					"encrypt": "mandatory",
					"trustServerCertificate": false,
					"authenticationType": "SQL",
					"userName": "[parameters('parsetrans_linkedservice_properties_typeProperties_userName')]",
					"password": {
						"type": "SecureString",
						"value": "[parameters('parsetrans_linkedservice_password')]"
					}
				}
			},
			"dependsOn": []
		},
		{
			"name": "[concat(parameters('factoryName'), '/parsetransotpt_linkedservice')]",
			"type": "Microsoft.DataFactory/factories/linkedServices",
			"apiVersion": "2018-06-01",
			"properties": {
				"annotations": [],
				"type": "AzureBlobStorage",
				"typeProperties": {
					"connectionString": "[parameters('parsetransotpt_linkedservice_connectionString')]"
				}
			},
			"dependsOn": []
		},
		{
			"name": "[concat(parameters('factoryName'), '/rtntopipe_dataset')]",
			"type": "Microsoft.DataFactory/factories/linkedServices",
			"apiVersion": "2018-06-01",
			"properties": {
				"annotations": [],
				"type": "AzureSqlDatabase",
				"typeProperties": {
					"server": "[parameters('rtntopipe_dataset_properties_typeProperties_server')]",
					"database": "[parameters('rtntopipe_dataset_properties_typeProperties_database')]",
					"encrypt": "mandatory",
					"trustServerCertificate": false,
					"authenticationType": "SQL",
					"userName": "[parameters('rtntopipe_dataset_properties_typeProperties_userName')]",
					"password": {
						"type": "SecureString",
						"value": "[parameters('rtntopipe_dataset_password')]"
					}
				}
			},
			"dependsOn": []
		},
		{
			"name": "[concat(parameters('factoryName'), '/rtntopipe_linkedservice')]",
			"type": "Microsoft.DataFactory/factories/linkedServices",
			"apiVersion": "2018-06-01",
			"properties": {
				"annotations": [],
				"type": "AzureBlobStorage",
				"typeProperties": {
					"connectionString": "[parameters('rtntopipe_linkedservice_connectionString')]"
				}
			},
			"dependsOn": []
		},
		{
			"name": "[concat(parameters('factoryName'), '/rtntopipeotpt_linkedservice')]",
			"type": "Microsoft.DataFactory/factories/linkedServices",
			"apiVersion": "2018-06-01",
			"properties": {
				"annotations": [],
				"type": "AzureBlobStorage",
				"typeProperties": {
					"connectionString": "[parameters('rtntopipeotpt_linkedservice_connectionString')]"
				}
			},
			"dependsOn": []
		},
		{
			"name": "[concat(parameters('factoryName'), '/stringify_linkedservice')]",
			"type": "Microsoft.DataFactory/factories/linkedServices",
			"apiVersion": "2018-06-01",
			"properties": {
				"annotations": [],
				"type": "AzureBlobStorage",
				"typeProperties": {
					"connectionString": "[parameters('stringify_linkedservice_connectionString')]"
				}
			},
			"dependsOn": []
		},
		{
			"name": "[concat(parameters('factoryName'), '/stringifyotpt_linkedservice')]",
			"type": "Microsoft.DataFactory/factories/linkedServices",
			"apiVersion": "2018-06-01",
			"properties": {
				"annotations": [],
				"type": "AzureBlobStorage",
				"typeProperties": {
					"connectionString": "[parameters('stringifyotpt_linkedservice_connectionString')]"
				}
			},
			"dependsOn": []
		},
		{
			"name": "[concat(parameters('factoryName'), '/template1_linkedservice')]",
			"type": "Microsoft.DataFactory/factories/linkedServices",
			"apiVersion": "2018-06-01",
			"properties": {
				"annotations": [],
				"type": "AzureBlobStorage",
				"typeProperties": {
					"connectionString": "[parameters('template1_linkedservice_connectionString')]"
				}
			},
			"dependsOn": []
		},
		{
			"name": "[concat(parameters('factoryName'), '/template_linkedservice')]",
			"type": "Microsoft.DataFactory/factories/linkedServices",
			"apiVersion": "2018-06-01",
			"properties": {
				"annotations": [],
				"type": "AzureBlobStorage",
				"typeProperties": {
					"connectionString": "[parameters('template_linkedservice_connectionString')]"
				}
			},
			"dependsOn": []
		}
	]
}